pilot_drive/__init__.py
pilot_drive/config.py
pilot_drive/main.py
pilot_drive/web/static/css/Futura.ttf
pilot_drive/web/static/css/pilot_style.css
pilot_drive/web/static/icons/adb_button.png
pilot_drive/web/static/icons/car_button.png
pilot_drive/web/static/icons/home_button.png
pilot_drive/web/static/icons/next_button.png
pilot_drive/web/static/icons/pause_button.png
pilot_drive/web/static/icons/play_button.png
pilot_drive/web/static/icons/prev_button.png
pilot_drive/web/static/icons/settings_button.png
pilot_drive/web/static/js/pilot-drive_script.js
pilot_drive/web/templates/home.html
utils/__init__.py
utils/adb_manager.py
utils/adb_notification.py
utils/adb_read_icon_db.py
utils/bt_ctl.py
utils/bt_track.py
utils/camera_manager.py
utils/obd_manager.py
utils/sys_utils.py
utils/update_manager.py
pilot_drive-1.0.9.dist-info/LICENSE
pilot_drive-1.0.9.dist-info/METADATA
pilot_drive-1.0.9.dist-info/WHEEL
pilot_drive-1.0.9.dist-info/top_level.txt
pilot_drive-1.0.9.dist-info/RECORD
