Metadata-Version: 2.1
Name: pilot-drive
Version: 1.0.9
Summary: PILOT Drive is a modular vehicle head unit built in Python
Home-page: https://github.com/lamemakes/pilot-drive
Author: Wesley Appler
Author-email: wes@lamemakes.com
License: UNKNOWN
Project-URL: Bug Tracker, https://github.com/lamemakes/pilot-drive/issues
Platform: UNKNOWN
Classifier: Programming Language :: Python :: 3
Classifier: License :: OSI Approved :: GNU General Public License v3 (GPLv3)
Classifier: Operating System :: Unix
Requires-Python: >=3.6
Requires-Dist: flask
Requires-Dist: obd
